askew3/__init__.py
askew3/image_transformer.py
askew3/util.py
askew3-0.0.1.dist-info/METADATA
askew3-0.0.1.dist-info/WHEEL
askew3-0.0.1.dist-info/top_level.txt
askew3-0.0.1.dist-info/RECORD
