Metadata-Version: 2.1
Name: askew3
Version: 0.0.1
Summary: 3D perspective transformation
Home-page: https://github.com/TheRincon/askew3
Author: Original Author: Hou-Ning Hu / @eborboihuc
Author-email: rinconrex@gmail.com
License: UNKNOWN
Platform: UNKNOWN
Classifier: Programming Language :: Python :: 3
Classifier: License :: OSI Approved :: MIT License
Classifier: Operating System :: OS Independent
Requires-Python: >=3.6
Requires-Dist: numpy
Requires-Dist: opencv-python
